{
  "channels": [
    {
      "id": "channel1",
      "name": "TeslaTravel",
      "niche": "trending travel & lifestyle moments",
      "format": "short",
      "visualStyle": "stockFootage",
      "madeForKids": false,
      "brandColorA": "#1b3a5c",
      "brandColorB": "#4f7dff",
      "refreshTokenEnv": "YT_REFRESH_TOKEN_CHANNEL1",
      "categoryId": "19",
      "tags": ["travel", "shorts", "trending"]
    },
    {
      "id": "channel2",
      "name": "Rainbow Little Learners",
      "niche": "toddler-friendly nursery rhymes, counting, colors, animal sounds and simple sing-along stories",
      "format": "long",
      "visualStyle": "stockFootage",
      "madeForKids": true,
      "brandColorA": "#ff6fae",
      "brandColorB": "#3ec6ff",
      "refreshTokenEnv": "YT_REFRESH_TOKEN_CHANNEL2",
      "categoryId": "27",
      "tags": ["kids", "nurseryrhymes", "toddlers", "kidssongs", "education"]
    }
  ]
}
